tentacular/__init__.py
tentacular/tenctarium.py
tentacular-0.1.1.dist-info/LICENSE.txt
tentacular-0.1.1.dist-info/WHEEL
tentacular-0.1.1.dist-info/METADATA
tentacular-0.1.1.dist-info/RECORD
