Metadata-Version: 2.1
Name: tentacular
Version: 0.1.1
Summary: M5Stack IoT Edge
License: MIT
Author: Mihails Delmans
Author-email: m.delmans@gmail.com
Requires-Python: >=3.7,<4.0
Classifier: License :: OSI Approved :: MIT License
Classifier: Programming Language :: Python :: 3
Classifier: Programming Language :: Python :: 3.7
Classifier: Programming Language :: Python :: 3.8
Requires-Dist: starlette (>=0.13.8,<0.14.0)
Requires-Dist: uvicorn (>=0.11.8,<0.12.0)
